huaweicloudsdkivs/__init__.py
huaweicloudsdkivs/v2/__init__.py
huaweicloudsdkivs/v2/ivs_async_client.py
huaweicloudsdkivs/v2/ivs_client.py
huaweicloudsdkivs/v2/model/__init__.py
huaweicloudsdkivs/v2/model/actions_list.py
huaweicloudsdkivs/v2/model/detect_extention_by_id_card_image_request.py
huaweicloudsdkivs/v2/model/detect_extention_by_id_card_image_response.py
huaweicloudsdkivs/v2/model/detect_extention_by_name_and_id_request.py
huaweicloudsdkivs/v2/model/detect_extention_by_name_and_id_response.py
huaweicloudsdkivs/v2/model/detect_standard_by_id_card_image_request.py
huaweicloudsdkivs/v2/model/detect_standard_by_id_card_image_response.py
huaweicloudsdkivs/v2/model/detect_standard_by_name_and_id_request.py
huaweicloudsdkivs/v2/model/detect_standard_by_name_and_id_response.py
huaweicloudsdkivs/v2/model/detect_standard_by_video_and_id_card_image_request.py
huaweicloudsdkivs/v2/model/detect_standard_by_video_and_id_card_image_response.py
huaweicloudsdkivs/v2/model/detect_standard_by_video_and_name_and_id_request.py
huaweicloudsdkivs/v2/model/detect_standard_by_video_and_name_and_id_response.py
huaweicloudsdkivs/v2/model/extention_req_data_by_id_card_image.py
huaweicloudsdkivs/v2/model/extention_req_data_by_name_and_id.py
huaweicloudsdkivs/v2/model/extention_resp_data_by_id_card_image.py
huaweicloudsdkivs/v2/model/extention_resp_data_by_name_and_id.py
huaweicloudsdkivs/v2/model/idcard_result.py
huaweicloudsdkivs/v2/model/ivs_extention_by_id_card_image_request_body.py
huaweicloudsdkivs/v2/model/ivs_extention_by_id_card_image_request_body_data.py
huaweicloudsdkivs/v2/model/ivs_extention_by_id_card_image_response_body_result.py
huaweicloudsdkivs/v2/model/ivs_extention_by_name_and_id_request_body.py
huaweicloudsdkivs/v2/model/ivs_extention_by_name_and_id_request_body_data.py
huaweicloudsdkivs/v2/model/ivs_extention_by_name_and_id_response_body_result.py
huaweicloudsdkivs/v2/model/ivs_standard_by_id_card_image_request_body.py
huaweicloudsdkivs-3.1.184.dist-info/METADATA
huaweicloudsdkivs-3.1.184.dist-info/WHEEL
huaweicloudsdkivs-3.1.184.dist-info/licenses/LICENSE
huaweicloudsdkivs-3.1.184.dist-info/RECORD
